ayetms_sau/__init__.py
ayetms_sau/__main__.py
ayetms_sau/main.py
ayetms_sau-0.1.2.dist-info/METADATA
ayetms_sau-0.1.2.dist-info/WHEEL
ayetms_sau-0.1.2.dist-info/entry_points.txt
ayetms_sau-0.1.2.dist-info/top_level.txt
ayetms_sau-0.1.2.dist-info/RECORD
