Metadata-Version: 2.1
Name: ayetms_sau
Version: 0.1.2
Summary: A CLI application for AYETMS
Home-page: https://github.com/yourusername/ayetms_sau
Author: Your Name
Author-email: your.email@example.com
Classifier: Programming Language :: Python :: 3
Classifier: License :: OSI Approved :: MIT License
Classifier: Operating System :: OS Independent
Requires-Python: >=3.6
Requires-Dist: requests
